dcontainer/__init__.py
dcontainer/__main__.py
dcontainer/py.typed
dcontainer/settings.py
dcontainer/apt/__init__.py
dcontainer/apt/apt_installer.py
dcontainer/apt_get/__init__.py
dcontainer/apt_get/apt_get_installer.py
dcontainer/aptitude/__init__.py
dcontainer/aptitude/aptitude_installer.py
dcontainer/cli/__init__.py
dcontainer/cli/generate.py
dcontainer/cli/install.py
dcontainer/devcontainer/__init__.py
dcontainer/devcontainer/oci_feature.py
dcontainer/devcontainer/oci_feature_installer.py
dcontainer/devcontainer/feature_generation/__init__.py
dcontainer/devcontainer/feature_generation/oci_feature_generator.py
dcontainer/devcontainer/feature_generation/dir_models/src_dir.py
dcontainer/devcontainer/feature_generation/dir_models/test_dir.py
dcontainer/devcontainer/feature_generation/file_models/dependencies_sh.py
dcontainer/devcontainer/feature_generation/file_models/devcontainer_feature_json.py
dcontainer/devcontainer/feature_generation/file_models/install_command_sh.py
dcontainer/devcontainer/feature_generation/file_models/install_sh.py
dcontainer/devcontainer/feature_generation/file_models/scenarios_json.py
dcontainer/devcontainer/feature_generation/file_models/test_sh.py
dcontainer/devcontainer/models/__init__.py
dcontainer/devcontainer/models/devcontainer_feature.py
dcontainer/devcontainer/models/devcontainer_feature_definition.py
dcontainer/gh_release/__init__.py
dcontainer/gh_release/gh_release_installer.py
dcontainer/oci/__init__.py
dcontainer/oci/oci_registry.py
dcontainer/snap/snap_installer.py
dcontainer/utils/__init__.py
dcontainer/utils/invoker.py
dcontainer/utils/linux_information_desk.py
dcontainer/utils/version.py
featurelayer-0.0.1.dist-info/METADATA
featurelayer-0.0.1.dist-info/WHEEL
featurelayer-0.0.1.dist-info/entry_points.txt
featurelayer-0.0.1.dist-info/top_level.txt
featurelayer-0.0.1.dist-info/RECORD
