Metadata-Version: 2.1
Name: featurelayer
Version: 0.0.1
Requires-Dist: pydantic (==1.10.5)
Requires-Dist: typer
Requires-Dist: invoke
Requires-Dist: semver (==2.13.0)
Provides-Extra: dev
Requires-Dist: pytest ; extra == 'dev'
Requires-Dist: pytest-shell-utilities ; extra == 'dev'
Requires-Dist: black ; extra == 'dev'
Requires-Dist: mypy ; extra == 'dev'
Requires-Dist: gitpython ; extra == 'dev'
Provides-Extra: generate
Requires-Dist: easyfs (==0.0.3) ; extra == 'generate'
